cuiows/__init__.py
cuiows/client.py
cuiows/exc.py
cuiows/wsproto/__init__.py
cuiows/wsproto/connection.py
cuiows/wsproto/events.py
cuiows/wsproto/extensions.py
cuiows/wsproto/frame_protocol.py
cuiows-0.1.10.dist-info/DESCRIPTION.rst
cuiows-0.1.10.dist-info/METADATA
cuiows-0.1.10.dist-info/RECORD
cuiows-0.1.10.dist-info/WHEEL
cuiows-0.1.10.dist-info/metadata.json
cuiows-0.1.10.dist-info/top_level.txt
